dita/__init__.py
dita/convert/__init__.py
dita/convert/__main__.py
dita/convert/cli.py
dita/convert/transform.py
dita/convert/xslt.py
dita/convert/xslt/common-templates.xsl
dita/convert/xslt/concept-generated.xsl
dita/convert/xslt/concept.xsl
dita/convert/xslt/reference-generated.xsl
dita/convert/xslt/reference.xsl
dita/convert/xslt/single-map.xsl
dita/convert/xslt/single-topic.xsl
dita/convert/xslt/task-generated.xsl
dita/convert/xslt/task.xsl
dita_convert-1.4.3.dist-info/licenses/LICENSE
dita_convert-1.4.3.dist-info/METADATA
dita_convert-1.4.3.dist-info/WHEEL
dita_convert-1.4.3.dist-info/entry_points.txt
dita_convert-1.4.3.dist-info/top_level.txt
dita_convert-1.4.3.dist-info/RECORD
